LICENCE.txt
MANIFEST.in
README.txt
__init__.py
setup.py
sfd.py
CreateAPI/__init__.py
CreateAPI.egg-info/PKG-INFO
CreateAPI.egg-info/SOURCES.txt
CreateAPI.egg-info/dependency_links.txt
CreateAPI.egg-info/requires.txt
CreateAPI.egg-info/top_level.txt
CreateAPI/functions/CreateAPI.py
CreateAPI/functions/__init__.py
CreateAPI/functions/jokes.txt
CreateAPI/functions/names.txt